enumtables/__init__.py
enumtables/alembic_autogen.py
enumtables/alembic_ops.py
enumtables/enum_column.py
enumtables/enum_table.py
SqlAlchemy_Enum_Tables-1.1.0.dist-info/METADATA
SqlAlchemy_Enum_Tables-1.1.0.dist-info/WHEEL
SqlAlchemy_Enum_Tables-1.1.0.dist-info/top_level.txt
SqlAlchemy_Enum_Tables-1.1.0.dist-info/RECORD
