Metadata-Version: 2.1
Name: SqlAlchemy-Enum-Tables
Version: 1.1.0
Summary: Making Python enums into SQLAlchemy tables with support for Alembic migrations
Home-page: https://git.heptacle.fr/neshiraini/sqlalchemy-enum-tables
Author: Nathan/Eilisha Shiraini
Author-email: neshiraini+sqlalchemy@heptacle.fr
License: Apache Software License
Keywords: sql sqlalchemy orm enum alembic migrations database relational
Platform: UNKNOWN
Classifier: Development Status :: 2 - Pre-Alpha
Classifier: License :: OSI Approved :: Apache Software License
Classifier: Programming Language :: Python :: 3
Classifier: Topic :: Database
Requires-Dist: sqlalchemy
Provides-Extra: alembic
Requires-Dist: alembic ; extra == 'alembic'
